pytest_consul/__init__.py
pytest_consul/plugin.py
test/__init__.py
test/conftest.py
test/test_live_server.py
test/test_plugin_config.py
test/test_ports.py
pytest_consul-0.2.0.dist-info/LICENSE
pytest_consul-0.2.0.dist-info/METADATA
pytest_consul-0.2.0.dist-info/WHEEL
pytest_consul-0.2.0.dist-info/entry_points.txt
pytest_consul-0.2.0.dist-info/top_level.txt
pytest_consul-0.2.0.dist-info/RECORD
