Metadata-Version: 2.1
Name: pytest-consul
Version: 0.2.0
Summary: pytest plugin with fixtures for testing consul aware apps
Home-page: http://github.com/daroot/pytest-consul
Author: Dan Root
Author-email: rootdan+pypi@gmail.com
License: WTFPL
Keywords: pytest,consul
Platform: any
Classifier: Development Status :: 3 - Alpha
Classifier: Framework :: Pytest
Classifier: Intended Audience :: Developers
Classifier: License :: Freely Distributable
Classifier: Operating System :: OS Independent
Classifier: Topic :: Software Development :: Testing
Classifier: Topic :: Software Development :: Quality Assurance
Classifier: Programming Language :: Python
Classifier: Programming Language :: Python :: 2.7
Classifier: Programming Language :: Python :: 3.5
Classifier: Programming Language :: Python :: 3.6
Classifier: Programming Language :: Python :: 3.7
Requires-Dist: pytest
Provides-Extra: all
Requires-Dist: pytest-timeout ; extra == 'all'
Requires-Dist: pytest-cov ; extra == 'all'
Requires-Dist: pytest ; extra == 'all'
Requires-Dist: requests ; extra == 'all'
Requires-Dist: pytest-flake8 ; extra == 'all'
Requires-Dist: configparser ; extra == 'all'
Provides-Extra: install
Requires-Dist: pytest ; extra == 'install'
Provides-Extra: setup
Requires-Dist: configparser ; extra == 'setup'
Provides-Extra: tests
Requires-Dist: pytest ; extra == 'tests'
Requires-Dist: pytest-cov ; extra == 'tests'
Requires-Dist: pytest-flake8 ; extra == 'tests'
Requires-Dist: pytest-timeout ; extra == 'tests'
Requires-Dist: requests ; extra == 'tests'
